{
  "features": [
    {
      "type": "Feature",
      "properties": {
        "place_name": "Madrid, Spain"
      },
      "geometry": {
        "coordinates": [
          -3.703269,
          40.417321
        ],
        "type": "Point"
      },
      "id": "21b72a7671386be629de3176cdb4250f"
    },
    {
      "type": "Feature",
      "properties": {
        "place_name": "Quepos, Costa Rica"
      },
      "geometry": {
        "coordinates": [
          -84.164844,
          9.432374
        ],
        "type": "Point"
      },
      "id": "49bd5ba87239c412004b5711ac2e31fe"
    },
    {
      "type": "Feature",
      "properties": {
        "place_name": "Beaver Creek, Colorado"
      },
      "geometry": {
        "coordinates": [
          -106.524634,
          39.632914
        ],
        "type": "Point"
      },
      "id": "8525e220d0965335013a49c4a435ae22"
    },
    {
      "type": "Feature",
      "properties": {
        "place_name": "Joshua Tree, California"
      },
      "geometry": {
        "coordinates": [
          -116.315366,
          34.134818
        ],
        "type": "Point"
      },
      "id": "85671c56e7782329f679b368e44bc302"
    },
    {
      "type": "Feature",
      "properties": {
        "place_name": "Nassau, Bahamas"
      },
      "geometry": {
        "coordinates": [
          -77.321721,
          25.075058
        ],
        "type": "Point"
      },
      "id": "90c2e2c6fd5abd666148d547acdb6eec"
    },
    {
      "type": "Feature",
      "properties": {
        "place_name": "Vienna, Austria"
      },
      "geometry": {
        "coordinates": [
          16.37656,
          48.218968
        ],
        "type": "Point"
      },
      "id": "c27b447ccfe11c93cb6df47763e364b1"
    },
    {
      "type": "Feature",
      "properties": {
        "place_name": "Birmingham, England"
      },
      "geometry": {
        "coordinates": [
          -1.89519,
          52.477551
        ],
        "type": "Point"
      },
      "id": "d37fcae9bd26f87f701bbf2927c82408"
    },
    {
      "type": "Feature",
      "properties": {
        "wikidata": "Q925598",
        "place_name": "San Angelo, Texas",
        "title": "Work trip"
      },
      "geometry": {
        "coordinates": [
          -100.4398,
          31.4648
        ],
        "type": "Point"
      },
      "id": "place.10000104017320570"
    },
    {
      "type": "Feature",
      "properties": {
        "wikidata": "Q128349",
        "place_name": "Wichita Falls, Texas"
      },
      "geometry": {
        "coordinates": [
          -98.4934,
          33.9137
        ],
        "type": "Point"
      },
      "id": "place.10001099925979110"
    },
    {
      "type": "Feature",
      "properties": {
        "wikidata": "Q23556",
        "place_name": "Atlanta, Georgia"
      },
      "geometry": {
        "coordinates": [
          -84.3902,
          33.7491
        ],
        "type": "Point"
      },
      "id": "place.10021883938173260"
    },
    {
      "type": "Feature",
      "properties": {
        "wikidata": "Q482993",
        "place_name": "Park City, Utah",
        "title": "1st ski trip"
      },
      "geometry": {
        "coordinates": [
          -111.498,
          40.6461
        ],
        "type": "Point"
      },
      "id": "place.10051900218692240"
    },
    {
      "type": "Feature",
      "properties": {
        "wikidata": "Q6106",
        "place_name": "Portland, Oregon"
      },
      "geometry": {
        "coordinates": [
          -122.6742,
          45.5202
        ],
        "type": "Point"
      },
      "id": "place.10052003640326360"
    },
    {
      "type": "Feature",
      "properties": {
        "wikidata": "Q80517",
        "place_name": "Shreveport, Louisiana"
      },
      "geometry": {
        "coordinates": [
          -93.7652,
          32.522199
        ],
        "type": "Point"
      },
      "id": "place.10077203198326230"
    },
    {
      "type": "Feature",
      "properties": {
        "wikidata": "Q16555",
        "place_name": "Houston, Texas"
      },
      "geometry": {
        "coordinates": [
          -95.3677,
          29.7589
        ],
        "type": "Point"
      },
      "id": "place.10081286487172470"
    },
    {
      "type": "Feature",
      "properties": {
        "wikidata": "Q8652",
        "place_name": "Miami, Florida"
      },
      "geometry": {
        "coordinates": [
          -80.1937,
          25.7743
        ],
        "type": "Point"
      },
      "id": "place.10154304590122320"
    },
    {
      "type": "Feature",
      "properties": {
        "wikidata": "Q488004",
        "place_name": "Palm Springs, California"
      },
      "geometry": {
        "coordinates": [
          -116.5403,
          33.8246
        ],
        "type": "Point"
      },
      "id": "place.10179900012994340"
    },
    {
      "type": "Feature",
      "properties": {
        "wikidata": "Q36091",
        "place_name": "Minneapolis, Minnesota"
      },
      "geometry": {
        "coordinates": [
          -93.2655,
          44.9773
        ],
        "type": "Point"
      },
      "id": "place.10538553763885940"
    },
    {
      "type": "Feature",
      "properties": {
        "wikidata": "Q41211",
        "place_name": "San Juan, Puerto Rico"
      },
      "geometry": {
        "coordinates": [
          -66.0571,
          18.3744
        ],
        "type": "Point"
      },
      "id": "place.10785605255103880"
    },
    {
      "type": "Feature",
      "properties": {
        "wikidata": "Q975627",
        "place_name": "Bandera, Texas"
      },
      "geometry": {
        "coordinates": [
          -99.0725,
          29.727
        ],
        "type": "Point"
      },
      "id": "place.10936108314129460"
    },
    {
      "type": "Feature",
      "properties": {
        "wikidata": "Q737624",
        "place_name": "Vieques, Puerto Rico"
      },
      "geometry": {
        "coordinates": [
          -65.4371,
          18.1291
        ],
        "type": "Point"
      },
      "id": "place.1096202447726750"
    },
    {
      "type": "Feature",
      "properties": {
        "wikidata": "Q61",
        "place_name": "Washington, District of Columbia"
      },
      "geometry": {
        "coordinates": [
          -77.0366,
          38.895
        ],
        "type": "Point"
      },
      "id": "place.11387590027246050"
    },
    {
      "type": "Feature",
      "properties": {
        "wikidata": "Q49221",
        "place_name": "Scottsdale, Arizona"
      },
      "geometry": {
        "coordinates": [
          -111.8992,
          33.509099
        ],
        "type": "Point"
      },
      "id": "place.12997528431131080"
    },
    {
      "type": "Feature",
      "properties": {
        "wikidata": "Q365",
        "place_name": "Köln, Germany"
      },
      "geometry": {
        "coordinates": [
          6.95778,
          50.94222
        ],
        "type": "Point"
      },
      "id": "place.13498115301191980"
    },
    {
      "type": "Feature",
      "properties": {
        "wikidata": "Q172",
        "place_name": "Toronto, Canada"
      },
      "geometry": {
        "coordinates": [
          -79.3849,
          43.6529
        ],
        "type": "Point"
      },
      "id": "place.1521272661948910"
    },
    {
      "type": "Feature",
      "properties": {
        "wikidata": "Q38555",
        "place_name": "Santa Fe, New Mexico"
      },
      "geometry": {
        "coordinates": [
          -105.9378,
          35.687
        ],
        "type": "Point"
      },
      "id": "place.15638833731787650"
    },
    {
      "type": "Feature",
      "properties": {
        "wikidata": "Q981796",
        "place_name": "Katy, Texas"
      },
      "geometry": {
        "coordinates": [
          -95.8244,
          29.7858
        ],
        "type": "Point"
      },
      "id": "place.15743426363394700"
    },
    {
      "type": "Feature",
      "properties": {
        "wikidata": "Q2156427",
        "place_name": "Destin, Florida"
      },
      "geometry": {
        "coordinates": [
          -86.4958,
          30.3935
        ],
        "type": "Point"
      },
      "id": "place.16528799866682040"
    },
    {
      "type": "Feature",
      "properties": {
        "wikidata": "Q274120",
        "place_name": "Niagara Falls, Canada"
      },
      "geometry": {
        "coordinates": [
          -79.114,
          43.1001
        ],
        "type": "Point"
      },
      "id": "place.17591341950204610"
    },
    {
      "type": "Feature",
      "properties": {
        "wikidata": "Q485186",
        "place_name": "Key West, Florida"
      },
      "geometry": {
        "coordinates": [
          -81.7724,
          24.5626
        ],
        "type": "Point"
      },
      "id": "place.18742792475493240"
    },
    {
      "type": "Feature",
      "properties": {
        "wikidata": "Q16559",
        "place_name": "Austin, Texas"
      },
      "geometry": {
        "coordinates": [
          -97.7437,
          30.2711
        ],
        "type": "Point"
      },
      "id": "place.18974382268754850"
    },
    {
      "type": "Feature",
      "properties": {
        "wikidata": "Q49255",
        "place_name": "Tampa, Florida"
      },
      "geometry": {
        "coordinates": [
          -82.4584,
          27.9478
        ],
        "type": "Point"
      },
      "id": "place.1985001777147560"
    },
    {
      "type": "Feature",
      "properties": {
        "wikidata": "Q153494",
        "place_name": "Rothenburg ob der Tauber, Germany"
      },
      "geometry": {
        "coordinates": [
          10.17889,
          49.37722
        ],
        "type": "Point"
      },
      "id": "place.2506031631735150"
    },
    {
      "type": "Feature",
      "properties": {
        "wikidata": "Q60",
        "place_name": "New York, New York"
      },
      "geometry": {
        "coordinates": [
          -73.9808,
          40.7648
        ],
        "type": "Point"
      },
      "id": "place.3677094975964500"
    },
    {
      "type": "Feature",
      "properties": {
        "wikidata": "Q16557",
        "place_name": "Dallas, Texas",
        "title": "Home"
      },
      "geometry": {
        "coordinates": [
          -96.7969,
          32.7763
        ],
        "type": "Point"
      },
      "id": "place.3790103132701420"
    },
    {
      "type": "Feature",
      "properties": {
        "wikidata": "Q34404",
        "place_name": "New Orleans, Louisiana"
      },
      "geometry": {
        "coordinates": [
          -90.0701,
          29.9499
        ],
        "type": "Point"
      },
      "id": "place.3979495376473040"
    },
    {
      "type": "Feature",
      "properties": {
        "wikidata": "Q16554",
        "place_name": "Denver, Colorado"
      },
      "geometry": {
        "coordinates": [
          -104.9653,
          39.7348
        ],
        "type": "Point"
      },
      "id": "place.3994099986046320"
    },
    {
      "type": "Feature",
      "properties": {
        "wikidata": "Q1489",
        "place_name": "Mexico City, Mexico"
      },
      "geometry": {
        "coordinates": [
          -99.14556,
          19.41944
        ],
        "type": "Point"
      },
      "id": "place.5154037879100080"
    },
    {
      "type": "Feature",
      "properties": {
        "wikidata": "Q1735",
        "place_name": "Innsbruck, Austria"
      },
      "geometry": {
        "coordinates": [
          11.38333,
          47.26667
        ],
        "type": "Point"
      },
      "id": "place.5655469505447060"
    },
    {
      "type": "Feature",
      "properties": {
        "wikidata": "Q24639",
        "place_name": "Vancouver, Canada"
      },
      "geometry": {
        "coordinates": [
          -123.1139,
          49.2609
        ],
        "type": "Point"
      },
      "id": "place.5944060364130490"
    },
    {
      "type": "Feature",
      "properties": {
        "wikidata": "Q64",
        "place_name": "Berlin, Germany"
      },
      "geometry": {
        "coordinates": [
          13.38333,
          52.51667
        ],
        "type": "Point"
      },
      "id": "place.6996813740564380"
    },
    {
      "type": "Feature",
      "properties": {
        "wikidata": "Q1297",
        "place_name": "Chicago, Illinois"
      },
      "geometry": {
        "coordinates": [
          -87.6244,
          41.8756
        ],
        "type": "Point"
      },
      "id": "place.7071500072701850"
    },
    {
      "type": "Feature",
      "properties": {
        "wikidata": "Q44989",
        "place_name": "Tulsa, Oklahoma",
        "title": "Work trip"
      },
      "geometry": {
        "coordinates": [
          -95.9251,
          36.1012
        ],
        "type": "Point"
      },
      "id": "place.7151896155396020"
    },
    {
      "type": "Feature",
      "properties": {
        "wikidata": "Q1794",
        "place_name": "Frankfurt am Main, Germany"
      },
      "geometry": {
        "coordinates": [
          8.67972,
          50.11361
        ],
        "type": "Point"
      },
      "id": "place.7300924236190980"
    },
    {
      "type": "Feature",
      "properties": {
        "wikidata": "Q989988",
        "place_name": "Playa Del Carmen, Mexico"
      },
      "geometry": {
        "coordinates": [
          -87.08111,
          20.6275
        ],
        "type": "Point"
      },
      "id": "place.7482933334307120"
    },
    {
      "type": "Feature",
      "properties": {
        "wikidata": "Q1143416",
        "place_name": "Hot Springs National Park, Arkansas"
      },
      "geometry": {
        "coordinates": [
          -93.0552,
          34.5037
        ],
        "type": "Point"
      },
      "id": "place.7535375517368230"
    },
    {
      "type": "Feature",
      "properties": {
        "wikidata": "Q975",
        "place_name": "San Antonio, Texas"
      },
      "geometry": {
        "coordinates": [
          -98.4951,
          29.4246
        ],
        "type": "Point"
      },
      "id": "place.7705127234253710"
    },
    {
      "type": "Feature",
      "properties": {
        "wikidata": "Q1492",
        "place_name": "Barcelona, Spain"
      },
      "geometry": {
        "coordinates": [
          2.17694,
          41.3825
        ],
        "type": "Point"
      },
      "id": "place.8006288694167790"
    },
    {
      "type": "Feature",
      "properties": {
        "wikidata": "Q100",
        "place_name": "Boston, Massachusetts"
      },
      "geometry": {
        "coordinates": [
          -71.0596,
          42.3605
        ],
        "type": "Point"
      },
      "id": "place.8027400225012190"
    },
    {
      "type": "Feature",
      "properties": {
        "wikidata": "Q929946",
        "place_name": "Cozumel, Mexico"
      },
      "geometry": {
        "coordinates": [
          -86.94167,
          20.51667
        ],
        "type": "Point"
      },
      "id": "place.8160050749939920"
    },
    {
      "type": "Feature",
      "properties": {
        "wikidata": "Q1726",
        "place_name": "München, Germany"
      },
      "geometry": {
        "coordinates": [
          11.56667,
          48.13333
        ],
        "type": "Point"
      },
      "id": "place.8366109811859780"
    },
    {
      "type": "Feature",
      "properties": {
        "wikidata": "Q84",
        "place_name": "London, England"
      },
      "geometry": {
        "coordinates": [
          -0.1275,
          51.50722
        ],
        "type": "Point"
      },
      "id": "place.8500383470913397"
    },
    {
      "type": "Feature",
      "properties": {
        "wikidata": "Q5083",
        "place_name": "Seattle, Washington"
      },
      "geometry": {
        "coordinates": [
          -122.3301,
          47.6038
        ],
        "type": "Point"
      },
      "id": "place.9173935436229470"
    },
    {
      "type": "Feature",
      "properties": {
        "wikidata": "Q34713",
        "place_name": "Salzburg, Austria"
      },
      "geometry": {
        "coordinates": [
          13.03333,
          47.8
        ],
        "type": "Point"
      },
      "id": "place.9426904911259960"
    },
    {
      "type": "Feature",
      "properties": {
        "wikidata": "Q49233",
        "place_name": "Orlando, Florida"
      },
      "geometry": {
        "coordinates": [
          -81.379,
          28.5421
        ],
        "type": "Point"
      },
      "id": "place.9450099770250330"
    },
    {
      "type": "Feature",
      "properties": {
        "wikidata": "Q62",
        "place_name": "San Francisco, California"
      },
      "geometry": {
        "coordinates": [
          -122.463,
          37.7648
        ],
        "type": "Point"
      },
      "id": "place.9464292564361910"
    },
    {
      "type": "Feature",
      "properties": {
        "wikidata": "Q23768",
        "place_name": "Las Vegas, Nevada"
      },
      "geometry": {
        "coordinates": [
          -115.1492,
          36.1663
        ],
        "type": "Point"
      },
      "id": "place.9723284193317920"
    },
    {
      "type": "Feature",
      "properties": {
        "wikidata": "Q579736",
        "place_name": "Moline, Illinois",
        "title": "Work trip"
      },
      "geometry": {
        "coordinates": [
          -90.5151,
          41.5067
        ],
        "type": "Point"
      },
      "id": "place.9775286548394520"
    },
    {
      "type": "Feature",
      "properties": {
        "wikidata": "Q695511",
        "place_name": "College Station, Texas"
      },
      "geometry": {
        "coordinates": [
          -96.3347,
          30.6263
        ],
        "type": "Point"
      },
      "id": "place.9866505683031380"
    },
    {
      "type": "Feature",
      "properties": {
        "wikidata": "Q574612",
        "place_name": "New Braunfels, Texas"
      },
      "geometry": {
        "coordinates": [
          -98.1256,
          29.7026
        ],
        "type": "Point"
      },
      "id": "place.9956399580607880"
    },
    {
      "type": "Feature",
      "properties": {
        "wikidata": "Q65",
        "place_name": "Los Angeles, California"
      },
      "geometry": {
        "coordinates": [
          -118.2439,
          34.0544
        ],
        "type": "Point"
      },
      "id": "place.9962989141427640"
    },
    {
      "type": "Feature",
      "properties": {
        "wikidata": "Q16552",
        "place_name": "San Diego, California"
      },
      "geometry": {
        "coordinates": [
          -117.1628,
          32.717399
        ],
        "type": "Point"
      },
      "id": "place.9979692646618150"
    },
    {
      "type": "Feature",
      "properties": {
        "wikidata": "Q667507",
        "place_name": "Lake Powell, Utah"
      },
      "geometry": {
        "coordinates": [
          -111.469331,
          36.939671
        ],
        "type": "Point"
      },
      "id": "place.9981387657562290"
    },
    {
      "type": "Feature",
      "properties": {
        "short_code": "CR-SJ",
        "wikidata": "Q647808",
        "place_name": "San José, Costa Rica"
      },
      "geometry": {
        "coordinates": [
          -84.061293,
          9.634193
        ],
        "type": "Point"
      },
      "id": "region.3577"
    },
    {
      "type": "Feature",
      "properties": {
        "place_name": "Maui, Hawaii"
      },
      "geometry": {
        "type": "Point",
        "coordinates": [
          -156.6911745071411,
          20.924846422111663
        ]
      }
    },
    {
      "type": "Feature",
      "properties": {
        "place_name": "Hearst Castle,  San Simeon, California"
      },
      "geometry": {
        "type": "Point",
        "coordinates": [
          -121.18696689605711,
          35.650775385513334
        ]
      }
    },
    {
      "type": "Feature",
      "properties": {
        "place_name": "Astoria, Oregon"
      },
      "geometry": {
        "type": "Point",
        "coordinates": [
          -123.83651733398438,
          46.191001911142294
        ]
      }
    },
    {
      "type": "Feature",
      "properties": {
        "place_name": "Capitol Reef NP, Utah"
      },
      "geometry": {
        "type": "Point",
        "coordinates": [
          -111.48900032043456,
          38.30630499062284
        ]
      }
    },
    {
      "type": "Feature",
      "properties": {
        "place_name": "Neenah, Wisconsin"
      },
      "geometry": {
        "type": "Point",
        "coordinates": [
          -88.46268653869629,
          44.18589693286957
        ]
      }
    },
    {
      "type": "Feature",
      "properties": {
        "place_name": "Paris, France"
      },
      "geometry": {
        "type": "Point",
        "coordinates": [
          2.3448944091796875,
          48.85522811385678
        ]
      }
    },
    {
      "type": "Feature",
      "properties": {
        "place_name": "Rennes, France"
      },
      "geometry": {
        "type": "Point",
        "coordinates": [
          -1.669921875,
          48.11293286919236
        ]
      }
    },
    {
      "type": "Feature",
      "properties": {
        "place_name": "Rennes, France"
      },
      "geometry": {
        "type": "Point",
        "coordinates": [
          -1.669921875,
          48.11293286919236
        ]
      }
    },
    {
      "type": "Feature",
      "properties": {
        "place_name": "Mont Saint-Michel, France"
      },
      "geometry": {
        "type": "Point",
        "coordinates": [
          -1.5123367309570312,
          48.63585814062312
        ]
      }
    },
    {
      "type": "Feature",
      "properties": {
        "place_name": "Saint-Malo, France"
      },
      "geometry": {
        "type": "Point",
        "coordinates": [
          -2.0280075073242188,
          48.650603327742466
        ]
      }
    },
    {
      "type": "Feature",
      "properties": {
        "place_name": "Milan, Italy"
      },
      "geometry": {
        "type": "Point",
        "coordinates": [
          9.189462661743162,
          45.46467571396945
        ]
      }
    },
    {
      "type": "Feature",
      "properties": {
        "place_name": "Amsterdam, Netherlands"
      },
      "geometry": {
        "type": "Point",
        "coordinates": [
          4.9005889892578125,
          52.376647126933165
        ]
      }
    },
    {
      "type": "Feature",
      "properties": {
        "place_name": "Rotterdam, Netherlands"
      },
      "geometry": {
        "type": "Point",
        "coordinates": [
          4.469633102416992,
          51.92365231649078
        ]
      }
    },
    {
      "type": "Feature",
      "properties": {
        "place_name": "Punta Mita, Mexico"
      },
      "geometry": {
        "type": "Point",
        "coordinates": [
          -105.53719997406006,
          20.768192530190966
        ]
      }
    },
    {
      "type": "Feature",
      "properties": {
        "place_name": "Springdale, Arkansas"
      },
      "geometry": {
        "type": "Point",
        "coordinates": [
          -94.11918640136719,
          36.1822249804225
        ]
      }
    },
    {
      "type": "Feature",
      "properties": {
        "place_name": "Sydney, Australia"
      },
      "geometry": {
        "type": "Point",
        "coordinates": [
          151.20655596256256,
          -33.861275295301176
        ]
      }
    },
    {
      "type": "Feature",
      "properties": {
        "place_name": "Melbourne, Australia"
      },
      "geometry": {
        "type": "Point",
        "coordinates": [
          144.9765408039093,
          -37.80387360197311
        ]
      }
    },
    {
      "type": "Feature",
      "properties": {
        "place_name": "Byron Bay, Australia"
      },
      "geometry": {
        "type": "Point",
        "coordinates": [
          153.48881006240845,
          -28.626286676607677
        ]
      }
    },
    {
      "type": "Feature",
      "properties": {
        "place_name": "Brisbane, Australia"
      },
      "geometry": {
        "type": "Point",
        "coordinates": [
          153.02331268787384,
          -27.477630778681846
        ]
      }
    },
    {
      "type": "Feature",
      "properties": {
        "place_name": "Great Ocean Road, Australia"
      },
      "geometry": {
        "type": "Point",
        "coordinates": [
          143.01478385925293,
          -38.623039964254374
        ]
      }
    },
    {
      "type": "Feature",
      "properties": {
        "place_name": "Blue Mountains, Australia"
      },
      "geometry": {
        "type": "Point",
        "coordinates": [
          150.3120231628418,
          -33.73212048747284
        ]
      }
    },
    {
      "type": "Feature",
      "properties": {
        "place_name": "St. Louis, Missouri"
      },
      "geometry": {
        "type": "Point",
        "coordinates": [
          -90.20599365234375,
          38.63189092902837
        ]
      }
    },
    {
      "type": "Feature",
      "properties": {
        "place_name": "Osaka, Japan"
      },
      "geometry": {
        "type": "Point",
        "coordinates": [
          135.51936340332031,
          34.700965881347656
        ]
      }
    },
    {
      "type": "Feature",
      "properties": {
        "place_name": "Hiroshima, Japan"
      },
      "geometry": {
        "type": "Point",
        "coordinates": [
          132.45356750488281,
          34.395465850830078
        ]
      }
    },
    {
      "type": "Feature",
      "properties": {
        "place_name": "Miyajima, Japan"
      },
      "geometry": {
        "type": "Point",
        "coordinates": [
          132.31993103027344,
          34.295879364013672
        ]
      }
    },
    {
      "type": "Feature",
      "properties": {
        "place_name": "Kyoto, Japan"
      },
      "geometry": {
        "type": "Point",
        "coordinates": [
          135.75967407226562,
          34.98590087890625
        ]
      }
    },
    {
      "type": "Feature",
      "properties": {
        "place_name": "Tokyo, Japan"
      },
      "geometry": {
        "type": "Point",
        "coordinates": [
          139.73130798339844,
          35.662300109863281
        ]
      }
    },
    {
      "type": "Feature",
      "properties": {
        "place_name": "Mount Fuji, Japan"
      },
      "geometry": {
        "type": "Point",
        "coordinates": [
          138.57524108886719,
          35.469112396240234
        ]
      }
    },
    {
      "type": "Feature",
      "properties": {
        "place_name": "Sendai, Japan"
      },
      "geometry": {
        "type": "Point",
        "coordinates": [
          140.87619018554688,
          38.256324768066406
        ]
      }
    },
    {
      "type": "Feature",
      "properties": {
        "place_name": "Matsushima Bay, Japan"
      },
      "geometry": {
        "type": "Point",
        "coordinates": [
          141.15608215332031,
          38.325428009033203
        ]
      }
    },
    {
      "type": "Feature",
      "properties": {
        "place_name": "Sendai, Japan"
      },
      "geometry": {
        "type": "Point",
        "coordinates": [
          140.88168334960938,
          38.259830474853516
        ]
      }
    },
    {
      "type": "Feature",
      "properties": {
        "place_name": "Oirase Gorge, Japan"
      },
      "geometry": {
        "type": "Point",
        "coordinates": [
          140.98089599609375,
          40.575935363769531
        ]
      }
    },
    {
      "type": "Feature",
      "properties": {
        "place_name": "Hirosaki, Japan"
      },
      "geometry": {
        "type": "Point",
        "coordinates": [
          140.46710205078125,
          40.609371185302734
        ]
      }
    },
    {
      "type": "Feature",
      "properties": {
        "place_name": "Hachinohe, Japan"
      },
      "geometry": {
        "type": "Point",
        "coordinates": [
          141.5230712890625,
          40.52423095703125
        ]
      }
    },
    {
      "type": "Feature",
      "properties": {
        "place_name": "Orcas Island, Washington"
      },
      "geometry": {
        "type": "Point",
        "coordinates": [
          -122.86913299560547,
          48.705677032470703
        ]
      }
    },
    {
      "type": "Feature",
      "properties": {
        "place_name": "Rome, Italy"
      },
      "geometry": {
        "type": "Point",
        "coordinates": [
          12.475923538208008,
          41.89798355102539
        ]
      }
    },
    {
      "type": "Feature",
      "properties": {
        "place_name": "Positano, Italy"
      },
      "geometry": {
        "type": "Point",
        "coordinates": [
          14.488142967224121,
          40.627655029296875
        ]
      }
    },
    {
      "type": "Feature",
      "properties": {
        "place_name": "Venice, Italy"
      },
      "geometry": {
        "type": "Point",
        "coordinates": [
          12.33802604675293,
          45.43415069580078
        ]
      }
    },
    {
      "type": "Feature",
      "properties": {
        "place_name": "Florence, Italy"
      },
      "geometry": {
        "type": "Point",
        "coordinates": [
          11.260774612426758,
          43.753501892089844
        ]
      }
    },
    {
      "type": "Feature",
      "properties": {
        "place_name": "Capri, Italy"
      },
      "geometry": {
        "type": "Point",
        "coordinates": [
          14.228501319885254,
          40.55923843383789
        ]
      }
    },
    {
      "type": "Feature",
      "properties": {
        "place_name": "Amalfi, Italy"
      },
      "geometry": {
        "type": "Point",
        "coordinates": [
          14.601945877075195,
          40.63410568237305
        ]
      }
    },
    {
      "type": "Feature",
      "properties": {
        "place_name": "Sorrento, Italy"
      },
      "geometry": {
        "type": "Point",
        "coordinates": [
          14.412338256835938,
          40.647769927978516
        ]
      }
    },
    {
      "type": "Feature",
      "properties": {
        "place_name": "Vaduz, Liechtenstein"
      },
      "geometry": {
        "type": "Point",
        "coordinates": [
          9.5226001739501953,
          47.139453887939453
        ]
      }
    },
    {
      "type": "Feature",
      "properties": {
        "place_name": "Lucerne, Switzerland"
      },
      "geometry": {
        "type": "Point",
        "coordinates": [
          8.3090403795340357,
          47.051076192357485
        ]
      }
    },
    {
      "type": "Feature",
      "properties": {
        "place_name": "Dakota Dunes, South Dakota"
      },
      "geometry": {
        "type": "Point",
        "coordinates": [
          -96.481063842773438,
          42.503425598144531
        ]
      }
    },
    {
      "type": "Feature",
      "properties": {
        "place_name": "Oberammergau, Germany"
      },
      "geometry": {
        "type": "Point",
        "coordinates": [
          11.06248140335083,
          47.59934128833909
        ]
      }
    },
    {
      "type": "Feature",
      "properties": {
        "place_name": "Omaha, Nebraska"
      },
      "geometry": {
        "type": "Point",
        "coordinates": [
          -95.8993148803711,
          41.30205526045988
        ]
      }
    },
    {
      "type": "Feature",
      "properties": {
        "place_name": "Xpu-ha, Mexico"
      },
      "geometry": {
        "type": "Point",
        "coordinates": [
          -87.254280090332031,
          20.480180740356445
        ]
      }
    },
    {
      "type": "Feature",
      "properties": {
        "place_name": "Tulum, Mexico"
      },
      "geometry": {
        "type": "Point",
        "coordinates": [
          -87.458900451660156,
          20.14996337890625
        ]
      }
    },
    {
      "type": "Feature",
      "properties": {
        "place_name": "Sonoma, California"
      },
      "geometry": {
        "type": "Point",
        "coordinates": [
          -122.45893478393553,
          38.29263123752421
        ]
      }
    },
    {
      "type": "Feature",
      "properties": {
        "place_name": "Napa, California"
      },
      "geometry": {
        "type": "Point",
        "coordinates": [
          -122.28590011596678,
          38.297616056850146
        ]
      }
    },
    {
      "type": "Feature",
      "properties": {
        "place_name": "Sedona, Arizona"
      },
      "geometry": {
        "type": "Point",
        "coordinates": [
          -111.79344177246094,
          34.866778207689634
        ]
      }
    },
    {
      "type": "Feature",
      "properties": {
        "place_name": "Sausalito, California"
      },
      "geometry": {
        "type": "Point",
        "coordinates": [
          -122.4869155883789,
          37.859133539451456
        ]
      }
    },
    {
      "type": "Feature",
      "properties": {
        "place_name": "Great Smoky Mountains National Park"
      },
      "geometry": {
        "type": "Point",
        "coordinates": [
          -83.43841552734375,
          35.61823286113127
        ]
      }
    },
    {
      "type": "Feature",
      "properties": {
        "place_name": "Durant, Oklahoma"
      },
      "geometry": {
        "type": "Point",
        "coordinates": [
          -96.38683319091797,
          33.99745799229644
        ]
      }
    },
    {
      "type": "Feature",
      "properties": {
        "place_name": "Yountville, California"
      },
      "geometry": {
        "type": "Point",
        "coordinates": [
          -122.36673736572266,
          38.4056396484375
        ]
      }
    },
    {
      "type": "Feature",
      "properties": {
        "place_name": "Calistoga, California"
      },
      "geometry": {
        "type": "Point",
        "coordinates": [
          -122.54183959960938,
          38.55875778198242
        ]
      }
    },
    {
      "type": "Feature",
      "properties": {
        "place_name": "Miur Woods, California"
      },
      "geometry": {
        "type": "Point",
        "coordinates": [
          -122.5730209350586,
          37.8931770324707
        ]
      }
    },
    {
      "type": "Feature",
      "properties": {
        "place_name": "Marfa, Texas"
      },
      "geometry": {
        "type": "Point",
        "coordinates": [
          -104.03189849853516,
          30.305892944335938
        ]
      }
    },
    {
      "type": "Feature",
      "properties": {
        "place_name": "Pecos, Texas"
      },
      "geometry": {
        "type": "Point",
        "coordinates": [
          -103.4946060180664,
          31.425928115844727
        ]
      }
    },
    {
      "type": "Feature",
      "properties": {
        "place_name": "Van Horn, Texas"
      },
      "geometry": {
        "type": "Point",
        "coordinates": [
          -104.83133697509766,
          31.039356231689453
        ]
      }
    },
    {
      "type": "Feature",
      "properties": {
        "place_name": "Fort Davis, Texas"
      },
      "geometry": {
        "type": "Point",
        "coordinates": [
          -104.51840209960938,
          30.603588104248047
        ]
      }
    },
    {
      "type": "Feature",
      "properties": {
        "place_name": "Alpine, Texas"
      },
      "geometry": {
        "type": "Point",
        "coordinates": [
          -103.6611099243164,
          30.35765838623047
        ]
      }
    },
    {
      "type": "Feature",
      "properties": {
        "place_name": "Valentine, Texas"
      },
      "geometry": {
        "type": "Point",
        "coordinates": [
          -104.49552154541016,
          30.58406639099121
        ]
      }
    },
    {
      "type": "Feature",
      "properties": {
        "place_name": "Hope, Arkansas"
      },
      "geometry": {
        "type": "Point",
        "coordinates": [
          -93.58909606933594,
          33.67006843120305
        ]
      }
    },
    {
      "type": "Feature",
      "properties": {
        "place_name": "Culebra, Puerto Rico"
      },
      "geometry": {
        "type": "Point",
        "coordinates": [
          -65.30445098876953,
          18.313462715714387
        ]
      }
    },
    {
      "type": "Feature",
      "properties": {
        "place_name": "Athens, Greece"
      },
      "geometry": {
        "type": "Point",
        "coordinates": [
          23.72947883605957,
          37.971343994140625
        ]
      }
    },
    {
      "type": "Feature",
      "properties": {
        "place_name": "Meteora, Greece"
      },
      "geometry": {
        "type": "Point",
        "coordinates": [
          21.6300048828125,
          39.724941253662109
        ]
      }
    },
    {
      "type": "Feature",
      "properties": {
        "place_name": "Mykonos, Greece"
      },
      "geometry": {
        "type": "Point",
        "coordinates": [
          25.330057144165039,
          37.443477630615234
        ]
      }
    },
    {
      "type": "Feature",
      "properties": {
        "place_name": "Santorini, Greece"
      },
      "geometry": {
        "type": "Point",
        "coordinates": [
          25.381767272949219,
          36.462261199951172
        ]
      }
    },
    {
      "type": "Feature",
      "properties": {
        "place_name": "Delphi, Greece"
      },
      "geometry": {
        "type": "Point",
        "coordinates": [
          22.500654220581055,
          38.482498168945312
        ]
      }
    },
    {
      "type": "Feature",
      "properties": {
        "place_name": "Duluth, Minnesota"
      },
      "geometry": {
        "type": "Point",
        "coordinates": [
          -92.11212158203125,
          46.77279018059152
        ]
      }
    },
    {
      "type": "Feature",
      "properties": {
        "place_name": "Two Harbours, Minnesota"
      },
      "geometry": {
        "type": "Point",
        "coordinates": [
          -91.673431396484375,
          47.019401550292969
        ]
      }
    },
    {
      "type": "Feature",
      "properties": {
        "place_name": "Lisbon, Portugal"
      },
      "geometry": {
        "type": "Point",
        "coordinates": [
          -9.136548042297363,
          38.707649321049416
        ]
      }
    },
    {
      "type": "Feature",
      "properties": {
        "place_name": "Chamonix, France"
      },
      "geometry": {
        "type": "Point",
        "coordinates": [
          6.871433258056641,
          45.92402047860041
        ]
      }
    },
    {
      "type": "Feature",
      "properties": {
        "place_name": "Turks and Caicos"
      },
      "geometry": {
        "coordinates": [
          -72.2658947011372,
          21.785269384493077
        ],
        "type": "Point"
      }
    },
    {
      "type": "Feature",
      "properties": {
        "place_name": "Niseko, Japan"
      },
      "geometry": {
        "coordinates": [
          140.69374727719446,
          42.85181600019828
        ],
        "type": "Point"
      }
    },
    {
      "type": "Feature",
      "properties": {
        "place_name": "Nagano, Japan"
      },
      "geometry": {
        "coordinates": [
          138.18773773799273,
          36.66093526248031
        ],
        "type": "Point"
      }
    },
    {
      "type": "Feature",
      "properties": {
        "place_name": "Hakuba, Japan"
      },
      "geometry": {
        "coordinates": [
          137.83867717464375,
          36.70055784218698
        ],
        "type": "Point"
      }
    },
    {
      "type": "Feature",
      "properties": {
        "place_name": "Valencia, Spain"
      },
      "geometry": {
        "coordinates": [
          -0.37404838921526107,
          39.46991536861577
        ],
        "type": "Point"
      }
    },
    {
      "type": "Feature",
      "properties": {
        "place_name": "Mallorca, Spain"
      },
      "geometry": {
        "coordinates": [
          2.9658512989977055,
          39.652674663302065
        ],
        "type": "Point"
      }
    }
  ],
  "type": "FeatureCollection"
}
